zcbot_service_sdk/__init__.py
zcbot_service_sdk/callback.py
zcbot_service_sdk/client.py
zcbot_service_sdk/exceptions.py
zcbot_service_sdk/keys.py
zcbot_service_sdk/multi_thread.py
zcbot_service_sdk/utils.py
zcbot_service_sdk-0.0.2.dist-info/METADATA
zcbot_service_sdk-0.0.2.dist-info/WHEEL
zcbot_service_sdk-0.0.2.dist-info/top_level.txt
zcbot_service_sdk-0.0.2.dist-info/RECORD
